nobipy/__init__.py
nobipy/const.py
nobipy/exceptions.py
nobipy/main.py
nobipy-0.0.1.dist-info/METADATA
nobipy-0.0.1.dist-info/WHEEL
nobipy-0.0.1.dist-info/top_level.txt
nobipy-0.0.1.dist-info/RECORD
