Metadata-Version: 2.1
Name: nobipy
Version: 0.0.1
Summary: Nobitex cryptocurrency exchange python sdk
Home-page: https://github.com/amiwrpremium/nobipy
Author: amiwrpremium
Author-email: amiwrpremium@gmail.com
License: MIT
Project-URL: Bug Tracker, https://github.com/amiwrpremium/nobipy/issues
Keywords: nobitex,crypto,exchange,API,SDK
Platform: UNKNOWN
Classifier: Operating System :: OS Independent
Classifier: Topic :: Software Development :: Build Tools
Classifier: License :: OSI Approved :: MIT License
Classifier: Programming Language :: Python :: 3
Classifier: Programming Language :: Python :: 3.4
Classifier: Programming Language :: Python :: 3.5
Classifier: Programming Language :: Python :: 3.6
Classifier: Programming Language :: Python :: 3.7
Classifier: Programming Language :: Python :: 3.8
Classifier: Programming Language :: Python :: 3.9
Requires-Python: >=3.6
Requires-Dist: requests
Requires-Dist: simplejson
